{
  "recentFiles": [
    {
      "basename": "README",
      "path": "temp/README.md"
    },
    {
      "basename": "감평 2",
      "path": "temp/1. 단편/세이브로드/감평 2.md"
    },
    {
      "basename": "감평 1",
      "path": "temp/1. 단편/세이브로드/감평 1.md"
    },
    {
      "basename": "2.",
      "path": "temp/1. 단편/세이브로드/2..md"
    },
    {
      "basename": "1.",
      "path": "temp/1. 단편/세이브로드/1..md"
    },
    {
      "basename": "0.",
      "path": "temp/1. 단편/세이브로드/0..md"
    },
    {
      "basename": "던디감평",
      "path": "temp/0. 소재/던디감평.md"
    },
    {
      "basename": "학교생활부",
      "path": "temp/0. 소재/학교생활부.md"
    },
    {
      "basename": "0. 3천년 전",
      "path": "temp/1. 단편/3천년만에 부활한 마왕님/0. 3천년 전.md"
    },
    {
      "basename": "placeholder2",
      "path": "temp/3. 대회/placeholder2.md"
    },
    {
      "basename": "placeholder",
      "path": "temp/2. 장편/placeholder.md"
    },
    {
      "basename": "1. 2천년 전",
      "path": "temp/1. 단편/3천년만에 부활한 마왕님/1. 2천년 전.md"
    }
  ],
  "omittedPaths": [],
  "omittedTags": [],
  "updateOn": "file-open",
  "omitBookmarks": false
}